magicmath
